pypogo/__init__.py
pypogo/battle.py
pypogo/data.py
pypogo/meta.py
pypogo/meta_ultra.py
pypogo/pogo_api.py
pypogo/pokemon.py
pypogo/pvp_inventory.py
pypogo/pvp_teams.py
pypogo/pvpoke_driver.py
pypogo/qa.py
pypogo/utils/__init__.py
pypogo/utils/priority_queue.py
pypogo-0.1.0.dist-info/METADATA
pypogo-0.1.0.dist-info/WHEEL
pypogo-0.1.0.dist-info/top_level.txt
pypogo-0.1.0.dist-info/RECORD
